singer_best_practices_linter.py
singer_best_practices_linter-0.1.1.dist-info/DESCRIPTION.rst
singer_best_practices_linter-0.1.1.dist-info/METADATA
singer_best_practices_linter-0.1.1.dist-info/RECORD
singer_best_practices_linter-0.1.1.dist-info/WHEEL
singer_best_practices_linter-0.1.1.dist-info/entry_points.txt
singer_best_practices_linter-0.1.1.dist-info/metadata.json
singer_best_practices_linter-0.1.1.dist-info/top_level.txt
