Metadata-Version: 2.0
Name: singer-best-practices-linter
Version: 0.1.1
Summary: Linter for Singer Taps
Home-page: https://github.com/b-ryan/singer-best-practices-linter
Author: Buck Ryan
Author-email: UNKNOWN
License: UNKNOWN
Platform: UNKNOWN
Classifier: Programming Language :: Python :: 3 :: Only
